huscy/rooms/__init__.py
huscy/rooms/admin.py
huscy/rooms/models.py
huscy/rooms/serializer.py
huscy/rooms/services.py
huscy/rooms/urls.py
huscy/rooms/views.py
huscy/rooms/migrations/.gitignore
huscy/rooms/migrations/0001_initial.py
huscy/rooms/migrations/__init__.py
huscy_rooms-0.2.0a9.dist-info/METADATA
huscy_rooms-0.2.0a9.dist-info/WHEEL
huscy_rooms-0.2.0a9.dist-info/licenses/LICENSE
huscy_rooms-0.2.0a9.dist-info/RECORD
