Metadata-Version: 2.4
Name: huscy.rooms
Version: 0.2.0a9
Project-URL: homepage, https://bitbucket.org/huscy/rooms
Author-email: Stefan Bunde <stefanbunde+git@posteo.de>
License-Expression: AGPL-3.0-or-later
License-File: LICENSE
Classifier: Development Status :: 2 - Pre-Alpha
Classifier: Framework :: Django
Classifier: Framework :: Django :: 4.2
Classifier: Framework :: Django :: 5.1
Classifier: Framework :: Django :: 5.2
Classifier: Operating System :: OS Independent
Classifier: Programming Language :: Python
Classifier: Programming Language :: Python :: 3
Classifier: Programming Language :: Python :: 3 :: Only
Classifier: Programming Language :: Python :: 3.8
Classifier: Programming Language :: Python :: 3.9
Classifier: Programming Language :: Python :: 3.10
Classifier: Programming Language :: Python :: 3.11
Classifier: Programming Language :: Python :: 3.12
Classifier: Programming Language :: Python :: 3.13
Requires-Dist: django>=4.2
Requires-Dist: djangorestframework>=3.14
Provides-Extra: development
Requires-Dist: psycopg2-binary; extra == 'development'
Provides-Extra: testing
Requires-Dist: tox; extra == 'testing'
